{
    "Id":17677,
    "Name":"Crash the Ramparts",
    "Colors":"G",
    "Mana_cost":"{2}{G}",
    "Identity":"G",
    "Text":"Target creature gets +3/+3 and gains trample until end of turn.",
    "Effect":[
        {
            "Name":"crash_the_remparts",
            "Target":"creature",
			"Nb_target": 1,
			"Temporary": 1,
            "Activable":{
                
            },
            "Temporality":"play"
        }
    ],
    "Type":"Instant",
    "Subtype":null,
    "Supertype":null
}